<dict>
  <key>main-file</key>
  <string>/media/diskDrive/ahead/ahead_user12/AHEAD/KernelHLSStuff/Kernel_connected/KernelConnector/KernelConnector/hls/.autopilot/db/KernelConnector.pp.0.cpp</string>
  <key>diagnostics</key>
  <array>
    <dict>
      <key>level</key>
      <string>warning</string>
      <key>filename</key>
      <string>directive</string>
      <key>line</key>
      <integer>1</integer>
      <key>column</key>
      <integer>9</integer>
      <key>message</key>
      <string>HLS pragma dump _XLX_SEP_ PragmaIsValid=1_XLX_SEP_ PragmaType=top_XLX_SEP_ PragmaContext=directive_XLX_SEP_ PragmaFunction=Kernel_Connector_XLX_SEP_ PragmaOptions=name=Kernel_Connector_XLX_SEP_</string>
      <key>ID</key>
      <integer>5471</integer>
      <key>WarningOption</key>
      <string>dump-hls-pragmas</string>
    </dict>
    <dict>
      <key>level</key>
      <string>warning</string>
      <key>filename</key>
      <string>KernelConnector.cpp</string>
      <key>line</key>
      <integer>6</integer>
      <key>column</key>
      <integer>9</integer>
      <key>message</key>
      <string>HLS pragma dump _XLX_SEP_ PragmaIsValid=1_XLX_SEP_ PragmaType=interface_XLX_SEP_ PragmaContext=_XLX_SEP_ PragmaFunction=Kernel_Connector_XLX_SEP_ PragmaOptions=axis port = InputStream depth=3_XLX_SEP_</string>
      <key>ID</key>
      <integer>5471</integer>
      <key>WarningOption</key>
      <string>dump-hls-pragmas</string>
    </dict>
    <dict>
      <key>level</key>
      <string>warning</string>
      <key>filename</key>
      <string>KernelConnector.cpp</string>
      <key>line</key>
      <integer>9</integer>
      <key>column</key>
      <integer>9</integer>
      <key>message</key>
      <string>HLS pragma dump _XLX_SEP_ PragmaIsValid=1_XLX_SEP_ PragmaType=stream_XLX_SEP_ PragmaContext=_XLX_SEP_ PragmaFunction=Kernel_Connector_XLX_SEP_ PragmaOptions=variable=intermediateStream depth=3_XLX_SEP_</string>
      <key>ID</key>
      <integer>5471</integer>
      <key>WarningOption</key>
      <string>dump-hls-pragmas</string>
    </dict>
    <dict>
      <key>level</key>
      <string>warning</string>
      <key>filename</key>
      <string>KernelConnector.cpp</string>
      <key>line</key>
      <integer>10</integer>
      <key>column</key>
      <integer>9</integer>
      <key>message</key>
      <string>HLS pragma dump _XLX_SEP_ PragmaIsValid=1_XLX_SEP_ PragmaType=interface_XLX_SEP_ PragmaContext=_XLX_SEP_ PragmaFunction=Kernel_Connector_XLX_SEP_ PragmaOptions=axis port = intermediateStream depth=3_XLX_SEP_</string>
      <key>ID</key>
      <integer>5471</integer>
      <key>WarningOption</key>
      <string>dump-hls-pragmas</string>
    </dict>
  </array>
</dict>
