<root versionMajor = "1" versionMinor = "5">
  <kernel name="Kernel2Sum" language="c" vlnv="xilinx.com:hls:Kernel2Sum:1.0" attributes="" hash="" preferredWorkGroupSizeMultiple="0" workGroupSize="1" debug="false" compileOptions="" profileType="none" hwControlProtocol="ap_ctrl_chain">
    <ports>
      <port name="INPUTSTREAM" mode="read_only" dataWidth="32" portType="stream"/>
      <port name="OUTSTREAM" mode="write_only" dataWidth="32" portType="stream"/>
      <port name="S_AXI_CONTROL" portType="addressable" mode="slave" base="0x0" range="0x10" dataWidth="32"/>
    </ports>
    <args>
      <arg id="0" name="InputStream" addressQualifier="4" port="INPUTSTREAM" hostOffset="0x0" hostSize="0x8" offset="0x0" size="0x0" type="stream&lt;int, 0&gt;&amp;" origName="InputStream" origUse="variable"/>
      <arg id="1" name="OutStream" addressQualifier="4" port="OUTSTREAM" hostOffset="0x0" hostSize="0x8" offset="0x0" size="0x0" type="stream&lt;int, 0&gt;&amp;" origName="OutStream" origUse="variable"/>
    </args>
    <compileWorkGroupSize x="1" y="1" z="1"/>
    <maxWorkGroupSize x="1" y="1" z="1"/>
  </kernel>
</root>
